sso_ui_auth_client/__init__.py
sso_ui_auth_client/cas.py
sso_ui_auth_client/faculty_info.py
tests/__init__.py
tests/server.py
SSO_UI_auth_client_cas-1.0.0.dist-info/LICENSE
SSO_UI_auth_client_cas-1.0.0.dist-info/METADATA
SSO_UI_auth_client_cas-1.0.0.dist-info/WHEEL
SSO_UI_auth_client_cas-1.0.0.dist-info/top_level.txt
SSO_UI_auth_client_cas-1.0.0.dist-info/RECORD
